{
    "dao_symex_path_1.json": {
        "file_name": "",
        "from_function": "withdraw",
        "to_function": "transfer",
        "bug_type": "dao",
        "src_node": "\"BlockID: 28\nCall context: \nNone\nENTRY_POINT None\"",
        "dest_node": [
            "\"BlockID: 43\nCall context: \nTrue\nflag := false\""
        ],
        "executable_instructions": 64,
        "state_variable": "flag",
        "error": "",
        "result": "",
        "execution_details": ""
    },
    "dao_symex_path_2.json": {
        "file_name": "",
        "from_function": "withdraw",
        "to_function": "withdraw",
        "bug_type": "dao",
        "src_node": "\"BlockID: 45\nCall context: \nNone\nENTRY_POINT None\"",
        "dest_node": [
            "\"BlockID: 62\nCall context: \nTrue\nflag := false\""
        ],
        "executable_instructions": 69,
        "state_variable": "flag",
        "error": "",
        "result": "",
        "execution_details": ""
    },
    "dao_symex_path_3.json": {
        "file_name": "",
        "from_function": "withdraw",
        "to_function": "deposit",
        "bug_type": "dao",
        "src_node": "\"BlockID: 64\nCall context: \nNone\nENTRY_POINT None\"",
        "dest_node": [
            "\"BlockID: 78\nCall context: \nTrue\nflag := false\""
        ],
        "executable_instructions": 56,
        "state_variable": "flag",
        "error": "",
        "result": "",
        "execution_details": ""
    }
}