{
  "nodes": [
    "6",
    "7",
    "5[label=\"True\"]",
    "3",
    "5",
    "4",
    "TUPLE_0(bool,bytes) = LOW_LEVEL_CALL, dest:msg.sender, function:call, arguments:",
    "0",
    "10",
    "2[label=\"True\"]",
    "2",
    "6[label=\"False\"]",
    "1",
    "8[label=\"True\"]",
    "9",
    "8",
    "3[label=\"False\"]",
    "9[label=\"False\"]"
  ],
  "edges": [
    {
      "source": "0",
      "target": "1"
    },
    {
      "source": "1",
      "target": "2"
    },
    {
      "source": "2",
      "target": "3"
    },
    {
      "source": "3",
      "target": "4"
    },
    {
      "source": "0",
      "target": "1"
    },
    {
      "source": "1",
      "target": "2"
    },
    {
      "source": "0",
      "target": "1"
    },
    {
      "source": "1",
      "target": "2[label=\"True\"]"
    },
    {
      "source": "1",
      "target": "3[label=\"False\"]"
    },
    {
      "source": "3",
      "target": "4"
    },
    {
      "source": "4",
      "target": "5[label=\"True\"]"
    },
    {
      "source": "4",
      "target": "6[label=\"False\"]"
    },
    {
      "source": "6",
      "target": "7"
    },
    {
      "source": "7",
      "target": "8[label=\"True\"]"
    },
    {
      "source": "7",
      "target": "9[label=\"False\"]"
    },
    {
      "source": "8",
      "target": "9"
    },
    {
      "source": "9",
      "target": "10"
    },
    {
      "source": "0",
      "target": "1"
    },
    {
      "source": "1",
      "target": "2"
    }
  ]
}