{
  "nodes": [
    "balanceOf[msg.sender]",
    "REF_30(",
    "3",
    "balanceOf) = REF_11 - _value\"]",
    "REF_11(uint256)",
    "REF_5(uint256)",
    "REF_29(uint256)",
    "1",
    "assert(bool)(balanceOf",
    "REF_0(uint256)",
    "REF_23(",
    "frozenAccount) := freeze(bool)\"]",
    "REF_30(uint256)",
    "balanceOf",
    "balanceOf) = REF_6 - _value\"]",
    "balanceOf[_from]",
    "balanceOf) = REF_29 - _value\"]",
    "4",
    "REF_29(",
    "REF_9(uint256)",
    "REF_6(",
    "5",
    "REF_26(uint256)",
    "REF_6(uint256)",
    "require(bool)(! frozenAccount",
    "REF_3(uint256)",
    "REF_27(bool)",
    "frozenAccount[target]",
    "balanceOf) = REF_23 - _value\"]",
    "balanceOf) := totalSupply(uint256)\"]",
    "REF_25(uint256)",
    "REF_11(",
    "frozenAccount[_to]",
    "balanceOf[_to]",
    "7",
    "REF_10(uint256)",
    "REF_31(bool)",
    "8",
    "REF_8(uint256)",
    "REF_2(uint256)",
    "previousBalances = balanceOf",
    "frozenAccount[_from]",
    "REF_24(uint256)",
    "require(bool)(balanceOf",
    "6",
    "REF_1(uint256)",
    "REF_4(uint256)",
    "REF_7(",
    "0",
    "2",
    "REF_31(bool) (",
    "REF_22(uint256)",
    "REF_7(uint256)",
    "REF_0(uint256) (",
    "balanceOf) = REF_7 + _value\"]",
    "frozenAccount",
    "REF_28(bool)",
    "balanceOf) = REF_30 + _value\"]",
    "REF_23(uint256)"
  ],
  "edges": [
    {
      "source": "0",
      "target": "1"
    },
    {
      "source": "REF_0(uint256)",
      "target": "balanceOf[msg.sender]"
    },
    {
      "source": "REF_0(uint256) (",
      "target": "balanceOf) := totalSupply(uint256)\"]"
    },
    {
      "source": "0",
      "target": "1"
    },
    {
      "source": "1",
      "target": "2"
    },
    {
      "source": "0",
      "target": "2"
    },
    {
      "source": "2",
      "target": "1"
    },
    {
      "source": "0",
      "target": "1"
    },
    {
      "source": "REF_22(uint256)",
      "target": "balanceOf[msg.sender]"
    },
    {
      "source": "1",
      "target": "2"
    },
    {
      "source": "REF_23(uint256)",
      "target": "balanceOf[msg.sender]"
    },
    {
      "source": "REF_23(",
      "target": "balanceOf) = REF_23 - _value\"]"
    },
    {
      "source": "2",
      "target": "3"
    },
    {
      "source": "3",
      "target": "4"
    },
    {
      "source": "4",
      "target": "5"
    },
    {
      "source": "0",
      "target": "1"
    },
    {
      "source": "0",
      "target": "1"
    },
    {
      "source": "1",
      "target": "2"
    },
    {
      "source": "2",
      "target": "3"
    },
    {
      "source": "0",
      "target": "3"
    },
    {
      "source": "REF_31(bool)",
      "target": "frozenAccount[target]"
    },
    {
      "source": "REF_31(bool) (",
      "target": "frozenAccount) := freeze(bool)\"]"
    },
    {
      "source": "1",
      "target": "2"
    },
    {
      "source": "3",
      "target": "1"
    },
    {
      "source": "0",
      "target": "1"
    },
    {
      "source": "1",
      "target": "2"
    },
    {
      "source": "0",
      "target": "1"
    },
    {
      "source": "REF_10(uint256)",
      "target": "balanceOf[msg.sender]"
    },
    {
      "source": "1",
      "target": "2"
    },
    {
      "source": "REF_11(uint256)",
      "target": "balanceOf[msg.sender]"
    },
    {
      "source": "REF_11(",
      "target": "balanceOf) = REF_11 - _value\"]"
    },
    {
      "source": "2",
      "target": "3"
    },
    {
      "source": "3",
      "target": "4"
    },
    {
      "source": "4",
      "target": "5"
    },
    {
      "source": "0",
      "target": "1"
    },
    {
      "source": "1",
      "target": "2"
    },
    {
      "source": "0",
      "target": "1"
    },
    {
      "source": "1",
      "target": "2"
    },
    {
      "source": "REF_1(uint256)",
      "target": "balanceOf[_from]"
    },
    {
      "source": "2",
      "target": "3"
    },
    {
      "source": "REF_2(uint256)",
      "target": "balanceOf[_to]"
    },
    {
      "source": "REF_3(uint256)",
      "target": "balanceOf[_to]"
    },
    {
      "source": "3",
      "target": "4"
    },
    {
      "source": "REF_4(uint256)",
      "target": "balanceOf[_from]"
    },
    {
      "source": "REF_5(uint256)",
      "target": "balanceOf[_to]"
    },
    {
      "source": "4",
      "target": "5"
    },
    {
      "source": "REF_6(uint256)",
      "target": "balanceOf[_from]"
    },
    {
      "source": "REF_6(",
      "target": "balanceOf) = REF_6 - _value\"]"
    },
    {
      "source": "5",
      "target": "6"
    },
    {
      "source": "REF_7(uint256)",
      "target": "balanceOf[_to]"
    },
    {
      "source": "REF_7(",
      "target": "balanceOf) = REF_7 + _value\"]"
    },
    {
      "source": "6",
      "target": "7"
    },
    {
      "source": "7",
      "target": "8"
    },
    {
      "source": "REF_8(uint256)",
      "target": "balanceOf[_from]"
    },
    {
      "source": "REF_9(uint256)",
      "target": "balanceOf[_to]"
    },
    {
      "source": "0",
      "target": "2"
    },
    {
      "source": "2",
      "target": "1"
    },
    {
      "source": "0",
      "target": "1"
    },
    {
      "source": "1",
      "target": "2"
    },
    {
      "source": "REF_24(uint256)",
      "target": "balanceOf[_from]"
    },
    {
      "source": "2",
      "target": "3"
    },
    {
      "source": "REF_25(uint256)",
      "target": "balanceOf[_to]"
    },
    {
      "source": "REF_26(uint256)",
      "target": "balanceOf[_to]"
    },
    {
      "source": "3",
      "target": "4"
    },
    {
      "source": "REF_27(bool)",
      "target": "frozenAccount[_from]"
    },
    {
      "source": "4",
      "target": "5"
    },
    {
      "source": "REF_28(bool)",
      "target": "frozenAccount[_to]"
    },
    {
      "source": "5",
      "target": "6"
    },
    {
      "source": "REF_29(uint256)",
      "target": "balanceOf[_from]"
    },
    {
      "source": "REF_29(",
      "target": "balanceOf) = REF_29 - _value\"]"
    },
    {
      "source": "6",
      "target": "7"
    },
    {
      "source": "REF_30(uint256)",
      "target": "balanceOf[_to]"
    },
    {
      "source": "REF_30(",
      "target": "balanceOf) = REF_30 + _value\"]"
    },
    {
      "source": "7",
      "target": "8"
    },
    {
      "source": "0",
      "target": "1"
    },
    {
      "source": "1",
      "target": "2"
    },
    {
      "source": "0",
      "target": "1"
    },
    {
      "source": "1",
      "target": "2"
    },
    {
      "source": "2",
      "target": "3"
    }
  ]
}