{
  "nodes": [
    "0",
    "1",
    "2",
    "3",
    "4",
    "5",
    "6",
    "7",
    "8",
    "9",
    "IERC20(token).transfer(recipients",
    "LENGTH recipients",
    "REF_0(uint256)",
    "REF_0(uint256) (",
    "REF_1(uint256)",
    "REF_3",
    "REF_4(uint256)",
    "REF_5",
    "REF_7(address)",
    "TMP_13(bool) = HIGH_LEVEL_CALL, dest:TMP_12(IERC20), function:transfer, arguments:",
    "TMP_16(bool) = HIGH_LEVEL_CALL, dest:TMP_15(IERC20), function:transferFrom, arguments:",
    "TMP_7(bool) = HIGH_LEVEL_CALL, dest:TMP_6(IERC20), function:transfer, arguments:",
    "balances",
    "balances) := totalSupply(uint256)\"]",
    "recipients",
    "require(bool,string)(balances"
  ],
  "edges": [
    {
      "source": "0",
      "target": "1"
    },
    {
      "source": "REF_1(uint256)",
      "target": "balances"
    },
    {
      "source": "1",
      "target": "2"
    },
    {
      "source": "0",
      "target": "1"
    },
    {
      "source": "0",
      "target": "1"
    },
    {
      "source": "REF_3",
      "target": "LENGTH recipients"
    },
    {
      "source": "1",
      "target": "2"
    },
    {
      "source": "REF_4(uint256)",
      "target": "balances"
    },
    {
      "source": "2",
      "target": "5"
    },
    {
      "source": "3",
      "target": "6"
    },
    {
      "source": "4",
      "target": "9"
    },
    {
      "source": "5",
      "target": "3"
    },
    {
      "source": "REF_5",
      "target": "LENGTH recipients"
    },
    {
      "source": "6",
      "target": "7"
    },
    {
      "source": "6",
      "target": "4"
    },
    {
      "source": "REF_7(address)",
      "target": "recipients"
    },
    {
      "source": "7",
      "target": "8"
    },
    {
      "source": "8",
      "target": "6"
    },
    {
      "source": "0",
      "target": "1"
    },
    {
      "source": "1",
      "target": "2"
    },
    {
      "source": "0",
      "target": "1"
    },
    {
      "source": "1",
      "target": "2"
    },
    {
      "source": "REF_0(uint256)",
      "target": "balances"
    },
    {
      "source": "REF_0(uint256) (",
      "target": "balances) := totalSupply(uint256)\"]"
    }
  ]
}